motion_saver-0.1.0.dist-info/DESCRIPTION.rst
motion_saver-0.1.0.dist-info/METADATA
motion_saver-0.1.0.dist-info/RECORD
motion_saver-0.1.0.dist-info/WHEEL
motion_saver-0.1.0.dist-info/metadata.json
motion_saver-0.1.0.dist-info/top_level.txt
motionsaver/__init__.py
motionsaver/motionsaver.py
