Metadata-Version: 2.0
Name: motion-saver
Version: 0.1.0
Summary: Library to pick out motion from a stream of images.
Home-page: https://github.com/takeontom/motion-saver
Author: Tom Smith
Author-email: tom@takeontom.com
License: MIT license
Platform: UNKNOWN
Classifier: Development Status :: 2 - Pre-Alpha
Classifier: Intended Audience :: Developers
Classifier: License :: OSI Approved :: MIT License
Classifier: Natural Language :: English
Classifier: Programming Language :: Python :: 3.5
Classifier: Programming Language :: Python :: 3.6
Requires-Dist: pillow (>=4)
